CHANGES.rst
LICENSE.txt
MANIFEST.in
README.rst
setup.py
docs/architecture.png
src/bst/__init__.py
src/bst.pygasus.core.egg-info/PKG-INFO
src/bst.pygasus.core.egg-info/SOURCES.txt
src/bst.pygasus.core.egg-info/dependency_links.txt
src/bst.pygasus.core.egg-info/entry_points.txt
src/bst.pygasus.core.egg-info/namespace_packages.txt
src/bst.pygasus.core.egg-info/not-zip-safe
src/bst.pygasus.core.egg-info/requires.txt
src/bst.pygasus.core.egg-info/top_level.txt
src/bst/pygasus/__init__.py
src/bst/pygasus/core/__init__.py
src/bst/pygasus/core/applicationcontext.py
src/bst/pygasus/core/configure.zcml
src/bst/pygasus/core/ext.py
src/bst/pygasus/core/interfaces.py
src/bst/pygasus/core/resources.py
src/bst/pygasus/core/utils.py